main.py
kevo_mcp_fastmcp-0.1.1.dist-info/licenses/LICENSE
kevo_mcp_fastmcp-0.1.1.dist-info/METADATA
kevo_mcp_fastmcp-0.1.1.dist-info/WHEEL
kevo_mcp_fastmcp-0.1.1.dist-info/top_level.txt
kevo_mcp_fastmcp-0.1.1.dist-info/RECORD
