Metadata-Version: 2.4
Name: kevo-mcp-fastmcp
Version: 0.1.1
Summary: An MCP server giving you access to your data in Kevo
Project-URL: Homepage, https://github.com/fastmcp-me/kevo-mcp#readme
Project-URL: Repository, https://github.com/fastmcp-me/kevo-mcp.git
Project-URL: Issues, https://github.com/fastmcp-me/kevo-mcp/issues
Requires-Python: >=3.12
License-File: LICENSE
Requires-Dist: fastmcp>=2.3.4
Requires-Dist: pydantic>=2.0.0
Requires-Dist: python-kevo
Dynamic: license-file
